nornir_nuts/__init__.py
nornir_nuts/runners.py
nornir_nuts-0.1.0.dist-info/METADATA
nornir_nuts-0.1.0.dist-info/WHEEL
nornir_nuts-0.1.0.dist-info/entry_points.txt
nornir_nuts-0.1.0.dist-info/RECORD
